aioapi/__init__.py
aioapi/exceptions.py
aioapi/handlers.py
aioapi/inspect/__init__.py
aioapi/inspect/entities.py
aioapi/inspect/exceptions.py
aioapi/inspect/inspector.py
aioapi/middlewares.py
aioapi/py.typed
aioapi/routedef.py
aioapi/typedefs.py
aioapi-0.2.0.dist-info/LICENSE
aioapi-0.2.0.dist-info/WHEEL
aioapi-0.2.0.dist-info/METADATA
aioapi-0.2.0.dist-info/RECORD
